pysqream_sqlalchemy/__init__.py
pysqream_sqlalchemy/base.py
pysqream_sqlalchemy/dialect.py
pysqream_sqlalchemy-1.4.dist-info/METADATA
pysqream_sqlalchemy-1.4.dist-info/WHEEL
pysqream_sqlalchemy-1.4.dist-info/entry_points.txt
pysqream_sqlalchemy-1.4.dist-info/top_level.txt
pysqream_sqlalchemy-1.4.dist-info/RECORD
