Metadata-Version: 2.1
Name: pysqream-sqlalchemy
Version: 1.4
Summary: SQLAlchemy dialect for SQreamDB
Home-page: https://github.com/SQream/pysqream_sqlalchemy
Author: SQream
Author-email: info@sqream.com
License: UNKNOWN
Keywords: database sqlalchemy sqream sqreamdb
Platform: UNKNOWN
Classifier: Programming Language :: Python :: 3.9
Classifier: License :: OSI Approved :: BSD License
Classifier: Operating System :: OS Independent
Requires-Python: >=3.9
Requires-Dist: sqlalchemy==2.0.27
Requires-Dist: pysqream>=5.1.0
Requires-Dist: setuptools>=57.4.0
Requires-Dist: pandas==2.2.2
Requires-Dist: numpy==1.26.4
Requires-Dist: alembic>=1.10.2
